pen/__init__.py
pen/cli.py
pen/core.py
pen/edit.py
pen/storage.py
penpal-0.5.0.dist-info/LICENSE
penpal-0.5.0.dist-info/METADATA
penpal-0.5.0.dist-info/WHEEL
penpal-0.5.0.dist-info/entry_points.txt
penpal-0.5.0.dist-info/top_level.txt
penpal-0.5.0.dist-info/RECORD
