Metadata-Version: 2.1
Name: penpal
Version: 0.5.0
Summary: pen: terminal notes
Home-page: https://github.com/cwoebker/pen
Author: cwoebker
Author-email: me@cwoebker.com
License: BSD
Platform: UNKNOWN
Classifier: License :: OSI Approved :: BSD License
Classifier: Environment :: Console
Classifier: Natural Language :: English
Classifier: Intended Audience :: Developers
Classifier: Operating System :: OS Independent
Classifier: Topic :: Software Development
Classifier: Topic :: Terminals
Classifier: Topic :: Utilities
Classifier: Topic :: Text Processing
Classifier: Programming Language :: Python
Classifier: Programming Language :: Python :: 3
Classifier: Programming Language :: Python :: 3.6
Classifier: Programming Language :: Python :: 3.7
Classifier: Programming Language :: Python :: 3.8
Classifier: Programming Language :: Python :: Implementation :: CPython
Classifier: Programming Language :: Python :: Implementation :: PyPy
Requires-Python: >=3.6.0
Requires-Dist: clint
Requires-Dist: urwid
Requires-Dist: paxo (>=0.2.2)
